README.md
setup.py
pulumi_google_tag_manager/__init__.py
pulumi_google_tag_manager/service.py
pulumi_google_tag_manager.egg-info/PKG-INFO
pulumi_google_tag_manager.egg-info/SOURCES.txt
pulumi_google_tag_manager.egg-info/dependency_links.txt
pulumi_google_tag_manager.egg-info/requires.txt
pulumi_google_tag_manager.egg-info/top_level.txt
pulumi_google_tag_manager/dynamic_providers/__init__.py
pulumi_google_tag_manager/dynamic_providers/container.py
pulumi_google_tag_manager/dynamic_providers/container_provider.py
pulumi_google_tag_manager/dynamic_providers/custom_html_tag.py
pulumi_google_tag_manager/dynamic_providers/custom_html_tag_provider.py
pulumi_google_tag_manager/dynamic_providers/tag.py
pulumi_google_tag_manager/dynamic_providers/tag_provider.py
pulumi_google_tag_manager/dynamic_providers/workspace.py
pulumi_google_tag_manager/dynamic_providers/workspace_provider.py
pulumi_google_tag_manager/templates/__init__.py