Metadata-Version: 2.1
Name: pulumi-google-tag-manager
Version: 0.0.1
Summary: UNKNOWN
Home-page: https://github.com/nuage-studio/pulumi-google-tag-manager
License: UNKNOWN
Platform: UNKNOWN
Requires-Python: >=3.7
